flask_gatekeeper/__init__.py
flask_gatekeeper/gatekeeper.py
flask_gatekeeper/test_gatekeeper.py
flask_gatekeeper-1.0.0.dist-info/LICENSE
flask_gatekeeper-1.0.0.dist-info/METADATA
flask_gatekeeper-1.0.0.dist-info/WHEEL
flask_gatekeeper-1.0.0.dist-info/top_level.txt
flask_gatekeeper-1.0.0.dist-info/RECORD
