Metadata-Version: 2.1
Name: flask-gatekeeper
Version: 1.0.0
Summary: A (very) simple banning & rate limiting extension for Flask.
Home-page: https://github.com/k0rventen/flask-gatekeeper
Author: k0rventen
License: MIT
Platform: UNKNOWN
Classifier: Programming Language :: Python :: 3
Classifier: License :: OSI Approved :: MIT License
Requires-Python: >=3.7
License-File: LICENSE
Requires-Dist: Flask (>=1.1.*)
